lektor_google_tag_manager.py
lektor_google_tag_manager-0.1.dist-info/DESCRIPTION.rst
lektor_google_tag_manager-0.1.dist-info/METADATA
lektor_google_tag_manager-0.1.dist-info/RECORD
lektor_google_tag_manager-0.1.dist-info/WHEEL
lektor_google_tag_manager-0.1.dist-info/entry_points.txt
lektor_google_tag_manager-0.1.dist-info/metadata.json
lektor_google_tag_manager-0.1.dist-info/top_level.txt
