Metadata-Version: 2.0
Name: lektor-google-tag-manager
Version: 0.1
Summary: Adds support for Google Tag Manager to Lektor CMS
Home-page: http://github.com/JavierLopezMunoz/lektor-google-tag-manager/
Author: Javier Lopez
Author-email: javier@lopezmunoz.name
License: BSD
Platform: UNKNOWN
Classifier: Development Status :: 3 - Alpha
Classifier: Environment :: Console
Classifier: License :: OSI Approved :: BSD License
Classifier: Operating System :: OS Independent
Classifier: Programming Language :: Python
Classifier: Programming Language :: Python :: 2.7
Classifier: Programming Language :: Python :: 3
Classifier: Topic :: Internet :: WWW/HTTP
Classifier: Topic :: Software Development :: Libraries :: Python Modules
Requires-Dist: lektor
Requires-Dist: markupsafe
